pyhumour/__init__.py
pyhumour/main.py
pyhumour/_properties/__init__.py
pyhumour/_properties/adjective_absurdity.py
pyhumour/_properties/compatibility.py
pyhumour/_properties/conflict.py
pyhumour/_properties/inappropriateness.py
pyhumour/_properties/language_models.py
pyhumour/_properties/noun_absurdity.py
pyhumour/_properties/obviousness.py
pyhumour/_properties/requirements.txt
pyhumour/_utilities/__init__.py
pyhumour/_utilities/pos_tag_bigram_frequency_matrix.py
pyhumour/_utilities/preprocess.py
pyhumour/pyhumour.egg-info/SOURCES.txt
pyhumour/pyhumour.egg-info/dependency_links.txt
pyhumour/pyhumour.egg-info/requires.txt
pyhumour/pyhumour.egg-info/top_level.txt
pyhumour/resources/contraction_map.json
pyhumour/resources/ero-1gram-nostop-regexed.txt
pyhumour/tests/__init__.py
pyhumour/tests/properties/__init__.py
pyhumour/tests/properties/test_adjective_absurdity.py
pyhumour/tests/properties/test_compatibility.py
pyhumour/tests/properties/test_conflict.py
pyhumour/tests/properties/test_hmm.py
pyhumour/tests/properties/test_inappropriateness.py
pyhumour/tests/properties/test_ngram.py
pyhumour/tests/properties/test_noun_absurdity.py
pyhumour/tests/properties/test_obviousness.py
pyhumour/tests/utilities/__init__.py
pyhumour/tests/utilities/test_preprocess.py
pyhumour-0.1.1.dist-info/LICENSE
pyhumour-0.1.1.dist-info/METADATA
pyhumour-0.1.1.dist-info/WHEEL
pyhumour-0.1.1.dist-info/top_level.txt
pyhumour-0.1.1.dist-info/RECORD
