Metadata-Version: 2.1
Name: pyhumour
Version: 0.1.1
Summary: A module for the characterization and quantification of concise humour
Home-page: https://github.com/mellon-collie/pyhumour
Author: The PyHumour Development Team
Author-email: pyhumour-devs@googlegroups.com
License: BSD-3-Clause
Platform: UNKNOWN
Classifier: Programming Language :: Python :: 3
Classifier: License :: OSI Approved :: BSD License
Classifier: Operating System :: OS Independent
Requires-Python: >=3.6
Requires-Dist: pandas (>=0.23.4)
Requires-Dist: scipy (>=1.4.1)
Requires-Dist: numpy (>=1.13.0)
Requires-Dist: wordfreq (>=2.2.2)
Requires-Dist: hmmlearn (>=0.2.3)
Requires-Dist: nltk (>=3.3)
Requires-Dist: tensorflow (>=2.2)
Requires-Dist: keras (>=2.3.1)
Requires-Dist: requests (>=2.25.1)
Provides-Extra: dev
Requires-Dist: pytest (>=5.4) ; extra == 'dev'
Requires-Dist: twine (>=3.1) ; extra == 'dev'
Requires-Dist: nose (>=1.3.7) ; extra == 'dev'
Requires-Dist: nose-timer (>=1.0.1) ; extra == 'dev'
Requires-Dist: coverage (>=5.5) ; extra == 'dev'
